mocap_converter/__init__.py
mocap_converter/adjust_kinematic_tree.py
mocap_converter/kinematic_tree.py
mocap_converter/motion_data.py
mocap_converter/node.py
mocap_converter/pos2rot.py
mocap_converter/rot2pos.py
mocap_converter/adapter/azure_kinect.py
mocap_converter/io/bvh/channel_layout.py
mocap_converter/io/bvh/loader.py
mocap_converter/io/bvh/saver.py
mocap_converter/io/bvh/types.py
mocap_converter-0.0.1.dist-info/METADATA
mocap_converter-0.0.1.dist-info/WHEEL
mocap_converter-0.0.1.dist-info/licenses/LICENSE
mocap_converter-0.0.1.dist-info/RECORD
